key_guard.py
key_guard-0.1.dist-info/LICENSE
key_guard-0.1.dist-info/METADATA
key_guard-0.1.dist-info/WHEEL
key_guard-0.1.dist-info/entry_points.txt
key_guard-0.1.dist-info/top_level.txt
key_guard-0.1.dist-info/RECORD
