Metadata-Version: 2.1
Name: key-guard
Version: 0.1
Summary: A CLI tool to help you guard your sensitive information from being pushed to a remote repository
Home-page: https://github.com/buabaj/key-guard
Author: Jerry Buaba
Author-email: buabajerry@gmail.com
License: MIT
Platform: UNKNOWN
Classifier: Programming Language :: Python :: 3.8
Classifier: Operating System :: OS Independent
Requires-Python: >=3.8
Requires-Dist: autopep8 (==1.7.0)
Requires-Dist: click (==8.1.3)
Requires-Dist: pycodestyle (==2.9.1)
Requires-Dist: toml (==0.10.2)
